bosch_alarm_mode2/__init__.py
bosch_alarm_mode2/connection.py
bosch_alarm_mode2/const.py
bosch_alarm_mode2/history.py
bosch_alarm_mode2/history_const.py
bosch_alarm_mode2/panel.py
bosch_alarm_mode2/py.typed
bosch_alarm_mode2/utils.py
bosch_alarm_mode2-0.4.7.dist-info/METADATA
bosch_alarm_mode2-0.4.7.dist-info/WHEEL
bosch_alarm_mode2-0.4.7.dist-info/licenses/LICENSE
bosch_alarm_mode2-0.4.7.dist-info/RECORD
