Metadata-Version: 2.4
Name: bosch-alarm-mode2
Version: 0.4.7
Summary: An async Python library for interacting with Bosch Alarm Panels supporting the 'Mode 2' API.
Project-URL: Homepage, https://github.com/mag1024/bosch-alarm-mode2
Project-URL: Repository, https://github.com/mag1024/bosch-alarm-mode2.git
Project-URL: Issues, https://github.com/mag1024/bosch-alarm-mode2/issues
Author-email: Michael Grigoriev <mag@luminal.org>
License-Expression: MIT
License-File: LICENSE
Classifier: Development Status :: 5 - Production/Stable
Classifier: Intended Audience :: Developers
Classifier: Programming Language :: Python :: 3.11
Classifier: Programming Language :: Python :: 3.12
Classifier: Programming Language :: Python :: 3.13
Classifier: Topic :: Home Automation
Requires-Python: >=3.11
